odoo/addons/fieldservice_partner_multi_relation/README.rst
odoo/addons/fieldservice_partner_multi_relation/__init__.py
odoo/addons/fieldservice_partner_multi_relation/__manifest__.py
odoo/addons/fieldservice_partner_multi_relation/data/demo.xml
odoo/addons/fieldservice_partner_multi_relation/i18n/de.po
odoo/addons/fieldservice_partner_multi_relation/i18n/es.po
odoo/addons/fieldservice_partner_multi_relation/i18n/es_CL.po
odoo/addons/fieldservice_partner_multi_relation/i18n/fieldservice_partner_multi_relation.pot
odoo/addons/fieldservice_partner_multi_relation/i18n/it.po
odoo/addons/fieldservice_partner_multi_relation/i18n/pt_BR.po
odoo/addons/fieldservice_partner_multi_relation/i18n/pt_PT.po
odoo/addons/fieldservice_partner_multi_relation/models/__init__.py
odoo/addons/fieldservice_partner_multi_relation/models/fsm_location.py
odoo/addons/fieldservice_partner_multi_relation/models/res_partner.py
odoo/addons/fieldservice_partner_multi_relation/models/res_partner_relation_all.py
odoo/addons/fieldservice_partner_multi_relation/models/res_partner_relation_type.py
odoo/addons/fieldservice_partner_multi_relation/readme/CONFIGURE.rst
odoo/addons/fieldservice_partner_multi_relation/readme/CONTRIBUTORS.rst
odoo/addons/fieldservice_partner_multi_relation/readme/CREDITS.rst
odoo/addons/fieldservice_partner_multi_relation/readme/DESCRIPTION.rst
odoo/addons/fieldservice_partner_multi_relation/readme/INSTALL.rst
odoo/addons/fieldservice_partner_multi_relation/readme/ROADMAP.rst
odoo/addons/fieldservice_partner_multi_relation/readme/USAGE.rst
odoo/addons/fieldservice_partner_multi_relation/static/description/icon.png
odoo/addons/fieldservice_partner_multi_relation/static/description/index.html
odoo/addons/fieldservice_partner_multi_relation/views/fsm_location.xml
odoo/addons/fieldservice_partner_multi_relation/views/menu.xml
odoo12_addon_fieldservice_partner_multi_relation-12.0.1.0.0.99.dev25.dist-info/METADATA
odoo12_addon_fieldservice_partner_multi_relation-12.0.1.0.0.99.dev25.dist-info/WHEEL
odoo12_addon_fieldservice_partner_multi_relation-12.0.1.0.0.99.dev25.dist-info/top_level.txt
odoo12_addon_fieldservice_partner_multi_relation-12.0.1.0.0.99.dev25.dist-info/RECORD
